rio_mucho-1.0.0.dist-info/METADATA
rio_mucho-1.0.0.dist-info/RECORD
rio_mucho-1.0.0.dist-info/WHEEL
rio_mucho-1.0.0.dist-info/top_level.txt
riomucho/__init__.py
riomucho/single_process_pool.py
riomucho/utils.py
