Metadata-Version: 2.1
Name: rio-mucho
Version: 1.0.0
Summary: Windowed multiprocessing wrapper for rasterio
Home-page: https://github.com/mapbox/rio-mucho
Author: Damon Burgett
Author-email: damon@mapbox.com
License: MIT
Platform: UNKNOWN
Classifier: Programming Language :: Python :: 2.7
Classifier: Programming Language :: Python :: 3.5
Classifier: Programming Language :: Python :: 3.6
Provides-Extra: test
